RPG/__init__.py
RPG/baralho.py
RPG/iniciativa.py
RPG/dado/__init__.py
RPG/dado/dado.py
RPG/dado/dados.py
RPG/dado/rolar_dado_notacao.py
RPG/dado/helpers/__init__.py
RPG/dado/helpers/converter_notacao_dado.py
RPG/dado/helpers/monta_dado.py
RPG/sistemas/__init__.py
RPG/sistemas/dnd/__init__.py
RPG/sistemas/dnd/rola_tesouro.py
RPG/sistemas/dnd/teste.py
RPG/sistemas/dnd/data/__init__.py
RPG/sistemas/dnd/data/mecanicas.py
RPG/sistemas/dnd/data/tesouro.py
RPG/sistemas/dnd/helpers/__init__.py
RPG/sistemas/dnd/helpers/calcular_mod_atributo.py
RPG/sistemas/dnd/helpers/checa_testes.py
RPG/sistemas/pf2/PC.py
RPG/sistemas/pf2/__init__.py
RPG/sistemas/pf2/calcula_dano.py
RPG/sistemas/pf2/proficiencia.py
RPG/sistemas/pf2/data/__init__.py
RPG/sistemas/pf2/data/defesas_monstros.py
RPG/sistemas/pf2/data/proficiency.py
RPG/sistemas/pf2/data/saves.py
RPG/sistemas/pf2/data/skills.py
RPG/sistemas/pf2/data/tipos_ataques.py
RPG/sistemas/pf2/data/tipos_defesas.py
RPG/sistemas/pf2/helpers/__init__.py
RPG/sistemas/pf2/helpers/atributo.py
RPG/sistemas/pf2/helpers/base_calcula_dano.py
RPG/sistemas/pf2/helpers/proficiencias.py
RPG/sistemas/rolemaster/__init__.py
RPG/sistemas/rolemaster/consulta_critico.py
RPG/sistemas/rolemaster/data/__init__.py
RPG/sistemas/rolemaster/data/criticos.py
RPG/tabela_rolavel/__init__.py
RPG/tabela_rolavel/rolar_tabela.py
RPG/tabela_rolavel/tabela_rolavel.py
RPG/tabela_rolavel/helpers/__init__.py
RPG/tabela_rolavel/helpers/ajeita_tabela.py
RPG/tabela_rolavel/helpers/ajusta_resultados.py
RPG/tabela_rolavel/helpers/busca_index_item_tabela.py
RPG/tabela_rolavel/helpers/rolamento_dado.py
helpers/__init__.py
helpers/converter_notacao_dado.py
helpers/monta_dado.py
tests/__init__.py
TTRPGaag-3.0.1.dist-info/LICENSE
TTRPGaag-3.0.1.dist-info/METADATA
TTRPGaag-3.0.1.dist-info/WHEEL
TTRPGaag-3.0.1.dist-info/top_level.txt
TTRPGaag-3.0.1.dist-info/RECORD
