Metadata-Version: 2.1
Name: TTRPGaag
Version: 3.0.1
Summary: Pacote básico de Ferramentas de RPG em português
Author: Alessandro Guarita
Requires-Python: >=3.11
License-File: LICENSE
